README.md
main.py
setup.py
SeqArtFetch.egg-info/PKG-INFO
SeqArtFetch.egg-info/SOURCES.txt
SeqArtFetch.egg-info/dependency_links.txt
SeqArtFetch.egg-info/entry_points.txt
SeqArtFetch.egg-info/requires.txt
SeqArtFetch.egg-info/top_level.txt
SeqArtFetch.egg-info/zip-safe