Metadata-Version: 1.0
Name: SeqArtFetch
Version: 0.2.2
Summary: A near-universal webcomic/sequential art downloader.
Home-page: https://github.com/deingithub/SeqArtFetch
Author: deing
Author-email: admin@15318.de
License: MIT
Platform: UNKNOWN
